empdens/__init__.py
empdens/base.py
empdens/cade.py
empdens/data.py
empdens/names.py
empdens/tree.py
empdens/classifiers/__init__.py
empdens/classifiers/base.py
empdens/classifiers/lightgbm.py
empdens/evaluation/__init__.py
empdens/evaluation/binary.py
empdens/evaluation/evaluate.py
empdens/models/__init__.py
empdens/models/joint.py
empdens/models/multinomial.py
empdens/models/piecewise_uniform.py
empdens/resources/__init__.py
empdens/resources/data/__init__.py
empdens/resources/data/japanese_vowels.csv
empdens/simulators/__init__.py
empdens/simulators/bivariate.py
empdens/simulators/univariate.py
empdens/wrappers/__init__.py
empdens/wrappers/fast_kde.py
empdens/wrappers/sklearn_isolation_forest.py
empdens/wrappers/sklearn_kde.py
empdens-1.4.4.dist-info/METADATA
empdens-1.4.4.dist-info/WHEEL
empdens-1.4.4.dist-info/licenses/LICENSE
empdens-1.4.4.dist-info/RECORD
