Metadata-Version: 2.4
Name: empdens
Version: 1.4.4
Summary: Empirical density estimation
License-File: LICENSE
Requires-Python: >=3.10
Requires-Dist: lightgbm>=2.2.3
Requires-Dist: matplotlib>=3.0.3
Requires-Dist: pandahandler>=0.4.0
Requires-Dist: pandas>=0.24.2
Requires-Dist: psutil>=6.1.0
Requires-Dist: scikit-learn>=0.20.3
Requires-Dist: shmistogram>=1.0.0
Requires-Dist: typing-extensions>=4.12.2
